Samples/Verilog/Samples2/problem3.v
module problem3 (input wire A, B, C, D, E, output wire F);
	assign F = ((A || !B || C) && (!A || D) && (B || !C || !E)) ? 1'b1 : 1'b0;
endmodule

// module problem3 (input wire A, B, C, D, E,output reg F);
    // always @(*) begin
        // if ((A || !B || C) && (!A || D) && (B || !C || !E))
            // F = 1'b1;
        // else
            // F = 1'b0;
    // end
// endmodule

module problem3_tb;
reg A, B, C, D, E;
wire F;
problem3 uut(A, B, C, D, E, F);
initial begin
$dumpfile("problem3.vcd");
$dumpvars(0, problem3_tb);
$monitor("Time=%0t | A=%b B=%b C=%b D=%b E=%b |  F=%b", $time, A, B, C, D, E, F);
{A, B, C, D, E} = 4'b0000;
repeat (31) begin
#1 {A, B, C, D, E} = {A, B, C, D, E} + 1;
end
end
endmodule

Samples/Verilog/Samples2/problem3.vcd
$date
	Fri May 09 05:11:54 2025
$end
$version
	Icarus Verilog
$end
$timescale
	1s
$end
$scope module problem3_tb $end
$var wire 1 ! F $end
$var reg 1 " A $end
$var reg 1 # B $end
$var reg 1 $ C $end
$var reg 1 % D $end
$var reg 1 & E $end
$scope module uut $end
$var wire 1 " A $end
$var wire 1 # B $end
$var wire 1 $ C $end
$var wire 1 % D $end
$var wire 1 & E $end
$var wire 1 ! F $end
$upscope $end
$upscope $end
$enddefinitions $end
$comment Show the parameter values. $end
$dumpall
$end
#0
$dumpvars
0&
0%
0$
0#
0"
1!
$end
#1
1&
#2
1%
0&
#3
1&
#4
1$
0%
0&
#5
0!
1&
#6
1!
1%
0&
#7
0!
1&
#8
0!
1#
0$
0%
0&
#9
1&
#10
1%
0&
#11
1&
#12
1!
1$
0%
0&
#13
1&
#14
1%
0&
#15
1&
#16
0!
1"
0#
0$
0%
0&
#17
1&
#18
1!
1%
0&
#19
1&
#20
0!
1$
0%
0&
#21
1&
#22
1!
1%
0&
#23
0!
1&
#24
0!
1#
0$
0%
0&
#25
1&
#26
1!
1%
0&
#27
1&
#28
0!
1$
0%
0&
#29
1&
#30
1!
1%
0&
#31
1&
