Samples/Verilog/Samples2/problem1_sim.v
module problem1_design (output wire F, input wire A, B, C, D);
    assign F = (A & ~B) | (~C & D);
endmodule

module problem1_tb;
    reg A, B, C, D;
    wire F;
    problem1_design uut(F, A, B, C, D);
    initial begin
        {A, B, C, D} = 4'b0000;
        repeat (15) begin
            #1 {A, B, C, D} = {A, B, C, D} + 1;
        end
    end
    initial begin
        $monitor("Time=%0t | A=%b B=%b C=%b D=%b | F=%b", $time, A, B, C, D, F);
        $dumpfile("problem1_sim.vcd");
        $dumpvars(0, problem1_tb);
    end
endmodule

Samples/Verilog/Samples2/problem1_sim.vcd
$date
	Thu May 08 02:31:23 2025
$end
$version
	Icarus Verilog
$end
$timescale
	1s
$end
$scope module problem1_tb $end
$var wire 1 ! F $end
$var reg 1 " A $end
$var reg 1 # B $end
$var reg 1 $ C $end
$var reg 1 % D $end
$scope module uut $end
$var wire 1 " A $end
$var wire 1 # B $end
$var wire 1 $ C $end
$var wire 1 % D $end
$var wire 1 ! F $end
$upscope $end
$upscope $end
$enddefinitions $end
$comment Show the parameter values. $end
$dumpall
$end
#0
$dumpvars
0%
0$
0#
0"
0!
$end
#1
1!
1%
#2
0!
1$
0%
#3
1%
#4
1#
0$
0%
#5
1!
1%
#6
0!
1$
0%
#7
1%
#8
1!
1"
0#
0$
0%
#9
1%
#10
1$
0%
#11
1%
#12
0!
1#
0$
0%
#13
1!
1%
#14
0!
1$
0%
#15
1%
