Samples/Verilog/Samples2/roleda.v
module roleda1 (input wire A, B, C, D, E,  output wire F);
	assign F = (A + ~B + C) & (~A + D) & (B + ~C + ~E);
endmodule

module roleda1_tb; 
	reg A, B, C, D, E;
	wire F;
		roleda1 uut (A, B, C, D, E, F);
		initial begin
		{A, B, C, D, E} = 5'b00000;
		repeat (31) begin
			#1 {A, B, C, D} = {A, B, C, D} + 1;
		end
	end
	initial begin
		
		$monitor (" time=%0t A=%b B=%b C=%b D=%b E=%b F=%b", $time, A, B, C, D, E, F);
		
		$dumpfile ("roleda_1.vcd");
		
		$dumpvars (0, roleda1_tb);
		
	end
endmodule

Samples/Verilog/Samples2/roleda_2.vcd
$date
	Fri May 09 12:05:34 2025
$end
$version
	Icarus Verilog
$end
$timescale
	1s
$end
$scope module roleda1_tb $end
$var wire 1 ! F $end
$var reg 1 " A $end
$var reg 1 # B $end
$var reg 1 $ C $end
$var reg 1 % D $end
$var reg 1 & E $end
$scope module uut $end
$var wire 1 " A $end
$var wire 1 # B $end
$var wire 1 $ C $end
$var wire 1 % D $end
$var wire 1 & E $end
$var wire 1 ! F $end
$upscope $end
$upscope $end
$enddefinitions $end
$comment Show the parameter values. $end
$dumpall
$end
#0
$dumpvars
0&
0%
0$
0#
0"
0!
$end
#1
1%
#2
1$
0%
#3
1%
#4
1#
0$
0%
#5
1%
#6
1$
0%
#7
1%
#8
1"
0#
0$
0%
#9
1%
#10
1$
0%
#11
1!
1%
#12
0!
1#
0$
0%
#13
1!
1%
#14
0!
1$
0%
#15
1%
#16
0"
0#
0$
0%
#17
1%
#18
1$
0%
#19
1%
#20
1#
0$
0%
#21
1%
#22
1$
0%
#23
1%
#24
1"
0#
0$
0%
#25
1%
#26
1$
0%
#27
1!
1%
#28
0!
1#
0$
0%
#29
1!
1%
#30
0!
1$
0%
#31
1%
