Samples/Verilog/Samples2/problem2.v
module up_counter_4bit (input wire clk, input wire  rst, output reg [3:0] count);
    always @(posedge clk) begin
        if (rst)
            count <= 4'b0000;    
        else
            count <= count + 1;  
    end
endmodule


module tb_up_counter_4bit;
    reg clk;
    reg rst;
    wire [3:0] count;

    up_counter_4bit dut (.clk(clk), .rst(rst), .count(count));

    initial clk = 0;
    always #5 clk = ~clk;

    initial begin
        $display("clk\trst\tcount");
        $monitor("%b\t%b\t%b", clk, rst, count);
        $dumpfile("up_counter.vcd");
        $dumpvars(0, tb_up_counter_4bit);
        rst = 1;
        #10;
        rst = 0;
        #150;
        $finish;
    end

endmodule

Samples/Verilog/Samples2/up_counter.vcd
$date
	Mon May 19 00:10:53 2025
$end
$version
	Icarus Verilog
$end
$timescale
	1s
$end
$scope module tb_up_counter_4bit $end
$var wire 4 ! count [3:0] $end
$var reg 1 " clk $end
$var reg 1 # rst $end
$scope module dut $end
$var wire 1 " clk $end
$var wire 1 # rst $end
$var reg 4 $ count [3:0] $end
$upscope $end
$upscope $end
$enddefinitions $end
$comment Show the parameter values. $end
$dumpall
$end
#0
$dumpvars
bx $
1#
0"
bx !
$end
#5
b0 !
b0 $
1"
#10
0"
0#
#15
b1 !
b1 $
1"
#20
0"
#25
b10 !
b10 $
1"
#30
0"
#35
b11 !
b11 $
1"
#40
0"
#45
b100 !
b100 $
1"
#50
0"
#55
b101 !
b101 $
1"
#60
0"
#65
b110 !
b110 $
1"
#70
0"
#75
b111 !
b111 $
1"
#80
0"
#85
b1000 !
b1000 $
1"
#90
0"
#95
b1001 !
b1001 $
1"
#100
0"
#105
b1010 !
b1010 $
1"
#110
0"
#115
b1011 !
b1011 $
1"
#120
0"
#125
b1100 !
b1100 $
1"
#130
0"
#135
b1101 !
b1101 $
1"
#140
0"
#145
b1110 !
b1110 $
1"
#150
0"
#155
b1111 !
b1111 $
1"
