Samples/Verilog/Samples3/09_counter.v
module counter_09 (input wire clk, input wire rst, output reg [3:0] count);
    always @(posedge clk or posedge rst) begin
        if (rst)
            count <= 4'b0000;      
        else
            count <= count + 1;     
    end
endmodule

module tb_09_counter;
    reg clk, rst;
    wire [3:0] count;

    counter_09 uut (clk, rst, count);

    initial begin;
        clk = 0;
        rst = 1;
        #1 rst = 0;
            repeat (10) begin
                #1 clk = 1;
                #1 clk = 0;
            end
        $finish;
    end

    initial begin
        $dumpfile("0-9_counter.vcd");
        $dumpvars(0, tb_09_counter);
    end

    always @(posedge clk) begin
        if (!rst)
            $display("Time=%0t | rst=%b clk=%b | count=%b", $time, rst, clk, count);
    end
endmodule

Samples/Verilog/Samples3/0-9_down_counter.vcd
$date
	Mon Jun 02 03:49:13 2025
$end
$version
	Icarus Verilog
$end
$timescale
	1s
$end
$scope module tb_09_counter $end
$var wire 4 ! count [3:0] $end
$var reg 1 " clk $end
$var reg 1 # rst $end
$scope module uut $end
$var wire 1 " clk $end
$var wire 1 # rst $end
$var reg 4 $ count [3:0] $end
$upscope $end
$upscope $end
$enddefinitions $end
$comment Show the parameter values. $end
$dumpall
$end
#0
$dumpvars
b1001 $
1#
0"
b1001 !
$end
#1
b1000 !
b1000 $
1"
0#
#2
0"
#3
b111 !
b111 $
1"
#4
0"
#5
b110 !
b110 $
1"
#6
0"
#7
b101 !
b101 $
1"
#8
0"
#9
b100 !
b100 $
1"
#10
0"
#11
b11 !
b11 $
1"
#12
0"
#13
b10 !
b10 $
1"
#14
0"
#15
b1 !
b1 $
1"
#16
0"
#17
b0 !
b0 $
1"
#18
0"
#19
b1001 !
b1001 $
1"
#20
0"
#21
b1000 !
b1000 $
1"
#22
0"
#23
b111 !
b111 $
1"
#24
0"
#25
b110 !
b110 $
1"
#26
0"
#27
b101 !
b101 $
1"
#28
0"
#29
b100 !
b100 $
1"
#30
0"
#31
b11 !
b11 $
1"
#32
0"
#33
b10 !
b10 $
1"
#34
0"
#35
b1 !
b1 $
1"
#36
0"
#37
b0 !
b0 $
1"
#38
0"
#39
b1001 !
b1001 $
1"
#40
0"
#41
b1000 !
b1000 $
1"
#42
0"
#43
b111 !
b111 $
1"
#44
0"
#45
b110 !
b110 $
1"
#46
0"
#47
b101 !
b101 $
1"
#48
0"
#49
b100 !
b100 $
1"
#50
0"
#51
b11 !
b11 $
1"
#52
0"
#53
b10 !
b10 $
1"
#54
0"
#55
b1 !
b1 $
1"
#56
0"
#57
b0 !
b0 $
1"
#58
0"
#59
b1001 !
b1001 $
1"
#60
0"
#61
b1000 !
b1000 $
1"
#62
0"
#63
b111 !
b111 $
1"
#64
0"
#65
b110 !
b110 $
1"
#66
0"
#67
b101 !
b101 $
1"
#68
0"
#69
b100 !
b100 $
1"
#70
0"
#71
b11 !
b11 $
1"
#72
0"
#73
b10 !
b10 $
1"
#74
0"
#75
b1 !
b1 $
1"
#76
0"
#77
b0 !
b0 $
1"
#78
0"
#79
b1001 !
b1001 $
1"
#80
0"
#81
b1000 !
b1000 $
1"
#82
0"
#83
b111 !
b111 $
1"
#84
0"
#85
b110 !
b110 $
1"
#86
0"
#87
b101 !
b101 $
1"
#88
0"
#89
b100 !
b100 $
1"
#90
0"
#91
b11 !
b11 $
1"
#92
0"
#93
b10 !
b10 $
1"
#94
0"
#95
b1 !
b1 $
1"
#96
0"
#97
b0 !
b0 $
1"
#98
0"
#99
b1001 !
b1001 $
1"
#100
0"
#101
b1000 !
b1000 $
1"
#102
0"
#103
b111 !
b111 $
1"
#104
0"
#105
b110 !
b110 $
1"
#106
0"
#107
b101 !
b101 $
1"
#108
0"
#109
b100 !
b100 $
1"
#110
0"
#111
b11 !
b11 $
1"
#112
0"
#113
b10 !
b10 $
1"
#114
0"
#115
b1 !
b1 $
1"
#116
0"
#117
b0 !
b0 $
1"
#118
0"
#119
b1001 !
b1001 $
1"
#120
0"
#121
b1000 !
b1000 $
1"
#122
0"
#123
b111 !
b111 $
1"
#124
0"
#125
b110 !
b110 $
1"
#126
0"
#127
b101 !
b101 $
1"
#128
0"
#129
b100 !
b100 $
1"
#130
0"
#131
b11 !
b11 $
1"
#132
0"
#133
b10 !
b10 $
1"
#134
0"
#135
b1 !
b1 $
1"
#136
0"
#137
b0 !
b0 $
1"
#138
0"
#139
b1001 !
b1001 $
1"
#140
0"
#141
b1000 !
b1000 $
1"
#142
0"
#143
b111 !
b111 $
1"
#144
0"
#145
b110 !
b110 $
1"
#146
0"
#147
b101 !
b101 $
1"
#148
0"
#149
b100 !
b100 $
1"
#150
0"
#151
b11 !
b11 $
1"
#152
0"
#153
b10 !
b10 $
1"
#154
0"
#155
b1 !
b1 $
1"
#156
0"
#157
b0 !
b0 $
1"
#158
0"
#159
b1001 !
b1001 $
1"
#160
0"
#161
b1000 !
b1000 $
1"
#162
0"
#163
b111 !
b111 $
1"
#164
0"
#165
b110 !
b110 $
1"
#166
0"
#167
b101 !
b101 $
1"
#168
0"
#169
b100 !
b100 $
1"
#170
0"
#171
b11 !
b11 $
1"
#172
0"
#173
b10 !
b10 $
1"
#174
0"
#175
b1 !
b1 $
1"
#176
0"
#177
b0 !
b0 $
1"
#178
0"
#179
b1001 !
b1001 $
1"
#180
0"
#181
b1000 !
b1000 $
1"
#182
0"
#183
b111 !
b111 $
1"
#184
0"
#185
b110 !
b110 $
1"
#186
0"
#187
b101 !
b101 $
1"
#188
0"
#189
b100 !
b100 $
1"
#190
0"
#191
b11 !
b11 $
1"
#192
0"
#193
b10 !
b10 $
1"
#194
0"
#195
b1 !
b1 $
1"
#196
0"
#197
b0 !
b0 $
1"
#198
0"
#199
b1001 !
b1001 $
1"
#200
0"
#201
b1000 !
b1000 $
1"
#202
0"
#203
b111 !
b111 $
1"
#204
0"
#205
b110 !
b110 $
1"
#206
0"
#207
b101 !
b101 $
1"
#208
0"
#209
b100 !
b100 $
1"
#210
0"
#211
b11 !
b11 $
1"
#212
0"
#213
b10 !
b10 $
1"
#214
0"
#215
b1 !
b1 $
1"
#216
0"
#217
b0 !
b0 $
1"
#218
0"
#219
b1001 !
b1001 $
1"
#220
0"
#221
b1000 !
b1000 $
1"
#222
0"
#223
b111 !
b111 $
1"
#224
0"
#225
b110 !
b110 $
1"
#226
0"
#227
b101 !
b101 $
1"
#228
0"
#229
b100 !
b100 $
1"
#230
0"
#231
b11 !
b11 $
1"
#232
0"
#233
b10 !
b10 $
1"
#234
0"
#235
b1 !
b1 $
1"
#236
0"
#237
b0 !
b0 $
1"
#238
0"
#239
b1001 !
b1001 $
1"
#240
0"
#241
b1000 !
b1000 $
1"
#242
0"
#243
b111 !
b111 $
1"
#244
0"
#245
b110 !
b110 $
1"
#246
0"
#247
b101 !
b101 $
1"
#248
0"
#249
b100 !
b100 $
1"
#250
0"
#251
b11 !
b11 $
1"
#252
0"
#253
b10 !
b10 $
1"
#254
0"
#255
b1 !
b1 $
1"
#256
0"
#257
b0 !
b0 $
1"
#258
0"
#259
b1001 !
b1001 $
1"
#260
0"
#261
b1000 !
b1000 $
1"
#262
0"
#263
b111 !
b111 $
1"
#264
0"
#265
b110 !
b110 $
1"
#266
0"
#267
b101 !
b101 $
1"
#268
0"
#269
b100 !
b100 $
1"
#270
0"
#271
b11 !
b11 $
1"
#272
0"
#273
b10 !
b10 $
1"
#274
0"
#275
b1 !
b1 $
1"
#276
0"
#277
b0 !
b0 $
1"
#278
0"
#279
b1001 !
b1001 $
1"
#280
0"
#281
b1000 !
b1000 $
1"
#282
0"
#283
b111 !
b111 $
1"
#284
0"
#285
b110 !
b110 $
1"
#286
0"
#287
b101 !
b101 $
1"
#288
0"
#289
b100 !
b100 $
1"
#290
0"
#291
b11 !
b11 $
1"
#292
0"
#293
b10 !
b10 $
1"
#294
0"
#295
b1 !
b1 $
1"
#296
0"
#297
b0 !
b0 $
1"
#298
0"
#299
b1001 !
b1001 $
1"
#300
0"
#301
b1000 !
b1000 $
1"
#302
0"
#303
b111 !
b111 $
1"
#304
0"
#305
b110 !
b110 $
1"
#306
0"
#307
b101 !
b101 $
1"
#308
0"
#309
b100 !
b100 $
1"
#310
0"
#311
b11 !
b11 $
1"
#312
0"
#313
b10 !
b10 $
1"
#314
0"
#315
b1 !
b1 $
1"
#316
0"
#317
b0 !
b0 $
1"
#318
0"
#319
b1001 !
b1001 $
1"
#320
0"
#321
b1000 !
b1000 $
1"
#322
0"
#323
b111 !
b111 $
1"
#324
0"
#325
b110 !
b110 $
1"
#326
0"
#327
b101 !
b101 $
1"
#328
0"
#329
b100 !
b100 $
1"
#330
0"
#331
b11 !
b11 $
1"
#332
0"
#333
b10 !
b10 $
1"
#334
0"
#335
b1 !
b1 $
1"
#336
0"
#337
b0 !
b0 $
1"
#338
0"
#339
b1001 !
b1001 $
1"
#340
0"
#341
b1000 !
b1000 $
1"
#342
0"
#343
b111 !
b111 $
1"
#344
0"
#345
b110 !
b110 $
1"
#346
0"
#347
b101 !
b101 $
1"
#348
0"
#349
b100 !
b100 $
1"
#350
0"
#351
b11 !
b11 $
1"
#352
0"
#353
b10 !
b10 $
1"
#354
0"
#355
b1 !
b1 $
1"
#356
0"
#357
b0 !
b0 $
1"
#358
0"
#359
b1001 !
b1001 $
1"
#360
0"
#361
b1000 !
b1000 $
1"
#362
0"
#363
b111 !
b111 $
1"
#364
0"
#365
b110 !
b110 $
1"
#366
0"
#367
b101 !
b101 $
1"
#368
0"
#369
b100 !
b100 $
1"
#370
0"
#371
b11 !
b11 $
1"
#372
0"
#373
b10 !
b10 $
1"
#374
0"
#375
b1 !
b1 $
1"
#376
0"
#377
b0 !
b0 $
1"
#378
0"
#379
b1001 !
b1001 $
1"
#380
0"
#381
b1000 !
b1000 $
1"
#382
0"
#383
b111 !
b111 $
1"
#384
0"
#385
b110 !
b110 $
1"
#386
0"
#387
b101 !
b101 $
1"
#388
0"
#389
b100 !
b100 $
1"
#390
0"
#391
b11 !
b11 $
1"
#392
0"
#393
b10 !
b10 $
1"
#394
0"
#395
b1 !
b1 $
1"
#396
0"
#397
b0 !
b0 $
1"
#398
0"
#399
b1001 !
b1001 $
1"
#400
0"
#401
b1000 !
b1000 $
1"
#402
0"
#403
b111 !
b111 $
1"
#404
0"
#405
b110 !
b110 $
1"
#406
0"
#407
b101 !
b101 $
1"
#408
0"
#409
b100 !
b100 $
1"
#410
0"
#411
b11 !
b11 $
1"
#412
0"
#413
b10 !
b10 $
1"
#414
0"
#415
b1 !
b1 $
1"
#416
0"
#417
b0 !
b0 $
1"
#418
0"
#419
b1001 !
b1001 $
1"
#420
0"
#421
b1000 !
b1000 $
1"
#422
0"
#423
b111 !
b111 $
1"
#424
0"
#425
b110 !
b110 $
1"
#426
0"
#427
b101 !
b101 $
1"
#428
0"
#429
b100 !
b100 $
1"
#430
0"
#431
b11 !
b11 $
1"
#432
0"
#433
b10 !
b10 $
1"
#434
0"
#435
b1 !
b1 $
1"
#436
0"
#437
b0 !
b0 $
1"
#438
0"
#439
b1001 !
b1001 $
1"
#440
0"
#441
b1000 !
b1000 $
1"
#442
0"
#443
b111 !
b111 $
1"
#444
0"
#445
b110 !
b110 $
1"
#446
0"
#447
b101 !
b101 $
1"
#448
0"
#449
b100 !
b100 $
1"
#450
0"
#451
b11 !
b11 $
1"
#452
0"
#453
b10 !
b10 $
1"
#454
0"
#455
b1 !
b1 $
1"
#456
0"
#457
b0 !
b0 $
1"
#458
0"
#459
b1001 !
b1001 $
1"
#460
0"
#461
b1000 !
b1000 $
1"
#462
0"
#463
b111 !
b111 $
1"
#464
0"
#465
b110 !
b110 $
1"
#466
0"
#467
b101 !
b101 $
1"
#468
0"
#469
b100 !
b100 $
1"
#470
0"
#471
b11 !
b11 $
1"
#472
0"
#473
b10 !
b10 $
1"
#474
0"
#475
b1 !
b1 $
1"
#476
0"
#477
b0 !
b0 $
1"
#478
0"
#479
b1001 !
b1001 $
1"
#480
0"
#481
b1000 !
b1000 $
1"
#482
0"
#483
b111 !
b111 $
1"
#484
0"
#485
b110 !
b110 $
1"
#486
0"
#487
b101 !
b101 $
1"
#488
0"
#489
b100 !
b100 $
1"
#490
0"
#491
b11 !
b11 $
1"
#492
0"
#493
b10 !
b10 $
1"
#494
0"
#495
b1 !
b1 $
1"
#496
0"
#497
b0 !
b0 $
1"
#498
0"
#499
b1001 !
b1001 $
1"
#500
0"
#501
b1000 !
b1000 $
1"
#502
0"
#503
b111 !
b111 $
1"
#504
0"
#505
b110 !
b110 $
1"
#506
0"
#507
b101 !
b101 $
1"
#508
0"
#509
b100 !
b100 $
1"
#510
0"
#511
b11 !
b11 $
1"
#512
0"
#513
b10 !
b10 $
1"
#514
0"
#515
b1 !
b1 $
1"
#516
0"
#517
b0 !
b0 $
1"
#518
0"
#519
b1001 !
b1001 $
1"
#520
0"
#521
b1000 !
b1000 $
1"
#522
0"
#523
b111 !
b111 $
1"
#524
0"
#525
b110 !
b110 $
1"
#526
0"
#527
b101 !
b101 $
1"
#528
0"
#529
b100 !
b100 $
1"
#530
0"
#531
b11 !
b11 $
1"
#532
0"
#533
b10 !
b10 $
1"
#534
0"
#535
b1 !
b1 $
1"
#536
0"
#537
b0 !
b0 $
1"
#538
0"
#539
b1001 !
b1001 $
1"
#540
0"
#541
b1000 !
b1000 $
1"
#542
0"
#543
b111 !
b111 $
1"
#544
0"
#545
b110 !
b110 $
1"
#546
0"
#547
b101 !
b101 $
1"
#548
0"
#549
b100 !
b100 $
1"
#550
0"
#551
b11 !
b11 $
1"
#552
0"
#553
b10 !
b10 $
1"
#554
0"
#555
b1 !
b1 $
1"
#556
0"
#557
b0 !
b0 $
1"
#558
0"
#559
b1001 !
b1001 $
1"
#560
0"
#561
b1000 !
b1000 $
1"
#562
0"
#563
b111 !
b111 $
1"
#564
0"
#565
b110 !
b110 $
1"
#566
0"
#567
b101 !
b101 $
1"
#568
0"
#569
b100 !
b100 $
1"
#570
0"
#571
b11 !
b11 $
1"
#572
0"
#573
b10 !
b10 $
1"
#574
0"
#575
b1 !
b1 $
1"
#576
0"
#577
b0 !
b0 $
1"
#578
0"
#579
b1001 !
b1001 $
1"
#580
0"
#581
b1000 !
b1000 $
1"
#582
0"
#583
b111 !
b111 $
1"
#584
0"
#585
b110 !
b110 $
1"
#586
0"
#587
b101 !
b101 $
1"
#588
0"
#589
b100 !
b100 $
1"
#590
0"
#591
b11 !
b11 $
1"
#592
0"
#593
b10 !
b10 $
1"
#594
0"
#595
b1 !
b1 $
1"
#596
0"
#597
b0 !
b0 $
1"
#598
0"
#599
b1001 !
b1001 $
1"
#600
0"
#601
b1000 !
b1000 $
1"
#602
0"
#603
b111 !
b111 $
1"
#604
0"
#605
b110 !
b110 $
1"
#606
0"
#607
b101 !
b101 $
1"
#608
0"
#609
b100 !
b100 $
1"
#610
0"
#611
b11 !
b11 $
1"
#612
0"
#613
b10 !
b10 $
1"
#614
0"
#615
b1 !
b1 $
1"
#616
0"
#617
b0 !
b0 $
1"
#618
0"
#619
b1001 !
b1001 $
1"
#620
0"
#621
b1000 !
b1000 $
1"
#622
0"
#623
b111 !
b111 $
1"
#624
0"
#625
b110 !
b110 $
1"
#626
0"
#627
b101 !
b101 $
1"
#628
0"
#629
b100 !
b100 $
1"
#630
0"
#631
b11 !
b11 $
1"
#632
0"
#633
b10 !
b10 $
1"
#634
0"
#635
b1 !
b1 $
1"
#636
0"
#637
b0 !
b0 $
1"
#638
0"
#639
b1001 !
b1001 $
1"
#640
0"
#641
b1000 !
b1000 $
1"
#642
0"
#643
b111 !
b111 $
1"
#644
0"
#645
b110 !
b110 $
1"
#646
0"
#647
b101 !
b101 $
1"
#648
0"
#649
b100 !
b100 $
1"
#650
0"
#651
b11 !
b11 $
1"
#652
0"
#653
b10 !
b10 $
1"
#654
0"
#655
b1 !
b1 $
1"
#656
0"
#657
b0 !
b0 $
1"
#658
0"
#659
b1001 !
b1001 $
1"
#660
0"
#661
b1000 !
b1000 $
1"
#662
0"
#663
b111 !
b111 $
1"
#664
0"
#665
b110 !
b110 $
1"
#666
0"
#667
b101 !
b101 $
1"
#668
0"
#669
b100 !
b100 $
1"
#670
0"
#671
b11 !
b11 $
1"
#672
0"
#673
b10 !
b10 $
1"
#674
0"
#675
b1 !
b1 $
1"
#676
0"
#677
b0 !
b0 $
1"
#678
0"
#679
b1001 !
b1001 $
1"
#680
0"
#681
b1000 !
b1000 $
1"
#682
0"
#683
b111 !
b111 $
1"
#684
0"
#685
b110 !
b110 $
1"
#686
0"
#687
b101 !
b101 $
1"
#688
0"
#689
b100 !
b100 $
1"
#690
0"
#691
b11 !
b11 $
1"
#692
0"
#693
b10 !
b10 $
1"
#694
0"
#695
b1 !
b1 $
1"
#696
0"
#697
b0 !
b0 $
1"
#698
0"
#699
b1001 !
b1001 $
1"
#700
0"
#701
b1000 !
b1000 $
1"
#702
0"
#703
b111 !
b111 $
1"
#704
0"
#705
b110 !
b110 $
1"
#706
0"
#707
b101 !
b101 $
1"
#708
0"
#709
b100 !
b100 $
1"
#710
0"
#711
b11 !
b11 $
1"
#712
0"
#713
b10 !
b10 $
1"
#714
0"
#715
b1 !
b1 $
1"
#716
0"
#717
b0 !
b0 $
1"
#718
0"
#719
b1001 !
b1001 $
1"
#720
0"
#721
b1000 !
b1000 $
1"
#722
0"
#723
b111 !
b111 $
1"
#724
0"
#725
b110 !
b110 $
1"
#726
0"
#727
b101 !
b101 $
1"
#728
0"
#729
b100 !
b100 $
1"
#730
0"
#731
b11 !
b11 $
1"
#732
0"
#733
b10 !
b10 $
1"
#734
0"
#735
b1 !
b1 $
1"
#736
0"
#737
b0 !
b0 $
1"
#738
0"
#739
b1001 !
b1001 $
1"
#740
0"
#741
b1000 !
b1000 $
1"
#742
0"
#743
b111 !
b111 $
1"
#744
0"
#745
b110 !
b110 $
1"
#746
0"
#747
b101 !
b101 $
1"
#748
0"
#749
b100 !
b100 $
1"
#750
0"
#751
b11 !
b11 $
1"
#752
0"
#753
b10 !
b10 $
1"
#754
0"
#755
b1 !
b1 $
1"
#756
0"
#757
b0 !
b0 $
1"
#758
0"
#759
b1001 !
b1001 $
1"
#760
0"
#761
b1000 !
b1000 $
1"
#762
0"
#763
b111 !
b111 $
1"
#764
0"
#765
b110 !
b110 $
1"
#766
0"
#767
b101 !
b101 $
1"
#768
0"
#769
b100 !
b100 $
1"
#770
0"
#771
b11 !
b11 $
1"
#772
0"
#773
b10 !
b10 $
1"
#774
0"
#775
b1 !
b1 $
1"
#776
0"
#777
b0 !
b0 $
1"
#778
0"
#779
b1001 !
b1001 $
1"
#780
0"
#781
b1000 !
b1000 $
1"
#782
0"
#783
b111 !
b111 $
1"
#784
0"
#785
b110 !
b110 $
1"
#786
0"
#787
b101 !
b101 $
1"
#788
0"
#789
b100 !
b100 $
1"
#790
0"
#791
b11 !
b11 $
1"
#792
0"
#793
b10 !
b10 $
1"
#794
0"
#795
b1 !
b1 $
1"
#796
0"
#797
b0 !
b0 $
1"
#798
0"
#799
b1001 !
b1001 $
1"
#800
0"
#801
b1000 !
b1000 $
1"
#802
0"
#803
b111 !
b111 $
1"
#804
0"
#805
b110 !
b110 $
1"
#806
0"
#807
b101 !
b101 $
1"
#808
0"
#809
b100 !
b100 $
1"
#810
0"
#811
b11 !
b11 $
1"
#812
0"
#813
b10 !
b10 $
1"
#814
0"
#815
b1 !
b1 $
1"
#816
0"
#817
b0 !
b0 $
1"
#818
0"
#819
b1001 !
b1001 $
1"
#820
0"
#821
b1000 !
b1000 $
1"
#822
0"
#823
b111 !
b111 $
1"
#824
0"
#825
b110 !
b110 $
1"
#826
0"
#827
b101 !
b101 $
1"
#828
0"
#829
b100 !
b100 $
1"
#830
0"
#831
b11 !
b11 $
1"
#832
0"
#833
b10 !
b10 $
1"
#834
0"
#835
b1 !
b1 $
1"
#836
0"
#837
b0 !
b0 $
1"
#838
0"
#839
b1001 !
b1001 $
1"
#840
0"
#841
b1000 !
b1000 $
1"
#842
0"
#843
b111 !
b111 $
1"
#844
0"
#845
b110 !
b110 $
1"
#846
0"
#847
b101 !
b101 $
1"
#848
0"
#849
b100 !
b100 $
1"
#850
0"
#851
b11 !
b11 $
1"
#852
0"
#853
b10 !
b10 $
1"
#854
0"
#855
b1 !
b1 $
1"
#856
0"
#857
b0 !
b0 $
1"
#858
0"
#859
b1001 !
b1001 $
1"
#860
0"
#861
b1000 !
b1000 $
1"
#862
0"
#863
b111 !
b111 $
1"
#864
0"
#865
b110 !
b110 $
1"
#866
0"
#867
b101 !
b101 $
1"
#868
0"
#869
b100 !
b100 $
1"
#870
0"
#871
b11 !
b11 $
1"
#872
0"
#873
b10 !
b10 $
1"
#874
0"
#875
b1 !
b1 $
1"
#876
0"
#877
b0 !
b0 $
1"
#878
0"
#879
b1001 !
b1001 $
1"
#880
0"
#881
b1000 !
b1000 $
1"
#882
0"
#883
b111 !
b111 $
1"
#884
0"
#885
b110 !
b110 $
1"
#886
0"
#887
b101 !
b101 $
1"
#888
0"
#889
b100 !
b100 $
1"
#890
0"
#891
b11 !
b11 $
1"
#892
0"
#893
b10 !
b10 $
1"
#894
0"
#895
b1 !
b1 $
1"
#896
0"
#897
b0 !
b0 $
1"
#898
0"
#899
b1001 !
b1001 $
1"
#900
0"
#901
b1000 !
b1000 $
1"
#902
0"
#903
b111 !
b111 $
1"
#904
0"
#905
b110 !
b110 $
1"
#906
0"
#907
b101 !
b101 $
1"
#908
0"
#909
b100 !
b100 $
1"
#910
0"
#911
b11 !
b11 $
1"
#912
0"
#913
b10 !
b10 $
1"
#914
0"
#915
b1 !
b1 $
1"
#916
0"
#917
b0 !
b0 $
1"
#918
0"
#919
b1001 !
b1001 $
1"
#920
0"
#921
b1000 !
b1000 $
1"
#922
0"
#923
b111 !
b111 $
1"
#924
0"
#925
b110 !
b110 $
1"
#926
0"
#927
b101 !
b101 $
1"
#928
0"
#929
b100 !
b100 $
1"
#930
0"
#931
b11 !
b11 $
1"
#932
0"
#933
b10 !
b10 $
1"
#934
0"
#935
b1 !
b1 $
1"
#936
0"
#937
b0 !
b0 $
1"
#938
0"
#939
b1001 !
b1001 $
1"
#940
0"
#941
b1000 !
b1000 $
1"
#942
0"
#943
b111 !
b111 $
1"
#944
0"
#945
b110 !
b110 $
1"
#946
0"
#947
b101 !
b101 $
1"
#948
0"
#949
b100 !
b100 $
1"
#950
0"
#951
b11 !
b11 $
1"
#952
0"
#953
b10 !
b10 $
1"
#954
0"
#955
b1 !
b1 $
1"
#956
0"
#957
b0 !
b0 $
1"
#958
0"
#959
b1001 !
b1001 $
1"
#960
0"
#961
b1000 !
b1000 $
1"
#962
0"
#963
b111 !
b111 $
1"
#964
0"
#965
b110 !
b110 $
1"
#966
0"
#967
b101 !
b101 $
1"
#968
0"
#969
b100 !
b100 $
1"
#970
0"
#971
b11 !
b11 $
1"
#972
0"
#973
b10 !
b10 $
1"
#974
0"
#975
b1 !
b1 $
1"
#976
0"
#977
b0 !
b0 $
1"
#978
0"
#979
b1001 !
b1001 $
1"
#980
0"
#981
b1000 !
b1000 $
1"
#982
0"
#983
b111 !
b111 $
1"
#984
0"
#985
b110 !
b110 $
1"
#986
0"
#987
b101 !
b101 $
1"
#988
0"
#989
b100 !
b100 $
1"
#990
0"
#991
b11 !
b11 $
1"
#992
0"
#993
b10 !
b10 $
1"
#994
0"
#995
b1 !
b1 $
1"
#996
0"
#997
b0 !
b0 $
1"
#998
0"
#999
b1001 !
b1001 $
1"
#1000
0"
#1001
b1000 !
b1000 $
1"
#1002
0"
#1003
b111 !
b111 $
1"
#1004
0"
#1005
b110 !
b110 $
1"
#1006
0"
#1007
b101 !
b101 $
1"
#1008
0"
#1009
b100 !
b100 $
1"
#1010
0"
#1011
b11 !
b11 $
1"
#1012
0"
#1013
b10 !
b10 $
1"
#1014
0"
#1015
b1 !
b1 $
1"
#1016
0"
#1017
b0 !
b0 $
1"
#1018
0"
#1019
b1001 !
b1001 $
1"
#1020
0"
#1021
b1000 !
b1000 $
1"
#1022
0"
#1023
b111 !
b111 $
1"
#1024
0"
#1025
b110 !
b110 $
1"
#1026
0"
#1027
b101 !
b101 $
1"
#1028
0"
#1029
b100 !
b100 $
1"
#1030
0"
#1031
b11 !
b11 $
1"
#1032
0"
#1033
b10 !
b10 $
1"
#1034
0"
#1035
b1 !
b1 $
1"
#1036
0"
#1037
b0 !
b0 $
1"
#1038
0"
#1039
b1001 !
b1001 $
1"
#1040
0"
#1041
b1000 !
b1000 $
1"
#1042
0"
#1043
b111 !
b111 $
1"
#1044
0"
#1045
b110 !
b110 $
1"
#1046
0"
#1047
b101 !
b101 $
1"
#1048
0"
#1049
b100 !
b100 $
1"
#1050
0"
#1051
b11 !
b11 $
1"
#1052
0"
#1053
b10 !
b10 $
1"
#1054
0"
#1055
b1 !
b1 $
1"
#1056
0"
#1057
b0 !
b0 $
1"
#1058
0"
#1059
b1001 !
b1001 $
1"
#1060
0"
#1061
b1000 !
b1000 $
1"
#1062
0"
#1063
b111 !
b111 $
1"
#1064
0"
#1065
b110 !
b110 $
1"
#1066
0"
#1067
b101 !
b101 $
1"
#1068
0"
#1069
b100 !
b100 $
1"
#1070
0"
#1071
b11 !
b11 $
1"
#1072
0"
#1073
b10 !
b10 $
1"
#1074
0"
#1075
b1 !
b1 $
1"
#1076
0"
#1077
b0 !
b0 $
1"
#1078
0"
#1079
b1001 !
b1001 $
1"
#1080
0"
#1081
b1000 !
b1000 $
1"
#1082
0"
#1083
b111 !
b111 $
1"
#1084
0"
#1085
b110 !
b110 $
1"
#1086
0"
#1087
b101 !
b101 $
1"
#1088
0"
#1089
b100 !
b100 $
1"
#1090
0"
#1091
b11 !
b11 $
1"
#1092
0"
#1093
b10 !
b10 $
1"
#1094
0"
#1095
b1 !
b1 $
1"
#1096
0"
#1097
b0 !
b0 $
1"
#1098
0"
#1099
b1001 !
b1001 $
1"
#1100
0"
#1101
b1000 !
b1000 $
1"
#1102
0"
#1103
b111 !
b111 $
1"
#1104
0"
#1105
b110 !
b110 $
1"
#1106
0"
#1107
b101 !
b101 $
1"
#1108
0"
#1109
b100 !
b100 $
1"
#1110
0"
#1111
b11 !
b11 $
1"
#1112
0"
#1113
b10 !
b10 $
1"
#1114
0"
#1115
b1 !
b1 $
1"
#1116
0"
#1117
b0 !
b0 $
1"
#1118
0"
#1119
b1001 !
b1001 $
1"
#1120
0"
#1121
b1000 !
b1000 $
1"
#1122
0"
#1123
b111 !
b111 $
1"
#1124
0"
#1125
b110 !
b110 $
1"
#1126
0"
#1127
b101 !
b101 $
1"
#1128
0"
#1129
b100 !
b100 $
1"
#1130
0"
#1131
b11 !
b11 $
1"
#1132
0"
#1133
b10 !
b10 $
1"
#1134
0"
#1135
b1 !
b1 $
1"
#1136
0"
#1137
b0 !
b0 $
1"
#1138
0"
#1139
b1001 !
b1001 $
1"
#1140
0"
#1141
b1000 !
b1000 $
1"
#1142
0"
#1143
b111 !
b111 $
1"
#1144
0"
#1145
b110 !
b110 $
1"
#1146
0"
#1147
b101 !
b101 $
1"
#1148
0"
#1149
b100 !
b100 $
1"
#1150
0"
#1151
b11 !
b11 $
1"
#1152
0"
#1153
b10 !
b10 $
1"
#1154
0"
#1155
b1 !
b1 $
1"
#1156
0"
#1157
b0 !
b0 $
1"
#1158
0"
#1159
b1001 !
b1001 $
1"
#1160
0"
#1161
b1000 !
b1000 $
1"
#1162
0"
#1163
b111 !
b111 $
1"
#1164
0"
#1165
b110 !
b110 $
1"
#1166
0"
#1167
b101 !
b101 $
1"
#1168
0"
#1169
b100 !
b100 $
1"
#1170
0"
#1171
b11 !
b11 $
1"
#1172
0"
#1173
b10 !
b10 $
1"
#1174
0"
#1175
b1 !
b1 $
1"
#1176
0"
#1177
b0 !
b0 $
1"
#1178
0"
#1179
b1001 !
b1001 $
1"
#1180
0"
#1181
b1000 !
b1000 $
1"
#1182
0"
#1183
b111 !
b111 $
1"
#1184
0"
#1185
b110 !
b110 $
1"
#1186
0"
#1187
b101 !
b101 $
1"
#1188
0"
#1189
b100 !
b100 $
1"
#1190
0"
#1191
b11 !
b11 $
1"
#1192
0"
#1193
b10 !
b10 $
1"
#1194
0"
#1195
b1 !
b1 $
1"
#1196
0"
#1197
b0 !
b0 $
1"
#1198
0"
#1199
b1001 !
b1001 $
1"
#1200
0"
#1201
b1000 !
b1000 $
1"
#1202
0"
#1203
b111 !
b111 $
1"
#1204
0"
#1205
b110 !
b110 $
1"
#1206
0"
#1207
b101 !
b101 $
1"
#1208
0"
#1209
b100 !
b100 $
1"
#1210
0"
#1211
b11 !
b11 $
1"
#1212
0"
#1213
b10 !
b10 $
1"
#1214
0"
#1215
b1 !
b1 $
1"
#1216
0"
#1217
b0 !
b0 $
1"
#1218
0"
#1219
b1001 !
b1001 $
1"
#1220
0"
#1221
b1000 !
b1000 $
1"
#1222
0"
#1223
b111 !
b111 $
1"
#1224
0"
#1225
b110 !
b110 $
1"
#1226
0"
#1227
b101 !
b101 $
1"
#1228
0"
#1229
b100 !
b100 $
1"
#1230
0"
#1231
b11 !
b11 $
1"
#1232
0"
#1233
b10 !
b10 $
1"
#1234
0"
#1235
b1 !
b1 $
1"
#1236
0"
#1237
b0 !
b0 $
1"
#1238
0"
#1239
b1001 !
b1001 $
1"
#1240
0"
#1241
b1000 !
b1000 $
1"
#1242
0"
#1243
b111 !
b111 $
1"
#1244
0"
#1245
b110 !
b110 $
1"
#1246
0"
#1247
b101 !
b101 $
1"
#1248
0"
#1249
b100 !
b100 $
1"
#1250
0"
#1251
b11 !
b11 $
1"
#1252
0"
#1253
b10 !
b10 $
1"
#1254
0"
#1255
b1 !
b1 $
1"
#1256
0"
#1257
b0 !
b0 $
1"
#1258
0"
#1259
b1001 !
b1001 $
1"
#1260
0"
