Samples/Verilog/Samples1/sample5.v
module logic_circuit (output reg F, input A, B, C);
reg H, I, J, K;  

always @(A or B or C) begin
    if ((~A & ~B & ~C) == 1'b1) 
        H = 1'b1;
    else if ((~A & B & ~C) == 1'b1) 
        I = 1'b1;
    else if ((~A & ~B & C) == 1'b1) 
        J = 1'b1;
    else if ((~A & B & C) == 1'b1) 
        K = 1'b1;
    else begin
        H = 1'b0;
        I = 1'b0;
        J = 1'b0;
        K = 1'b0;
    end
    if ((H | I | J | K) == 1'b1) 
        F = 1'b1;
    else 
        F = 1'b0;
end
endmodule

Samples/Verilog/Samples1/sample5_tb.v
module logic_circuit_tb;
    reg A, B, C;  
    wire F;
    logic_circuit uut(F, A, B, C);
    initial begin
        A = 0; B = 0; C = 0;
        #1 A = 0; B = 0; C = 1;
        #1 A = 0; B = 1; C = 0;
        #1 A = 0; B = 1; C = 1;
        #1 A = 1; B = 0; C = 0;
        #1 A = 1; B = 0; C = 1;
        #1 A = 1; B = 1; C = 0;
        #1 A = 1; B = 1; C = 1;
    end
    initial begin
        $monitor("Time=%0t | A=%b B=%b C=%b | F=%b", $time, A, B, C, F);
        $dumpfile("logic_circuit_tb.vcd");
        $dumpvars(0, logic_circuit_tb);
    end
endmodule

Samples/Verilog/logic_circuit_tb.vcd
$date
	Sun Mar 09 10:45:36 2025
$end
$version
	Icarus Verilog
$end
$timescale
	1s
$end
$scope module logic_circuit_tb $end
$var wire 1 ! F $end
$var reg 1 " A $end
$var reg 1 # B $end
$var reg 1 $ C $end
$scope module uut $end
$var wire 1 " A $end
$var wire 1 # B $end
$var wire 1 $ C $end
$var reg 1 ! F $end
$var reg 1 % H $end
$var reg 1 & I $end
$var reg 1 ' J $end
$var reg 1 ( K $end
$upscope $end
$upscope $end
$enddefinitions $end
$comment Show the parameter values. $end
$dumpall
$end
#0
$dumpvars
x(
x'
x&
1%
0$
0#
0"
1!
$end
#1
1'
1$
#2
1&
0$
1#
#3
1(
1$
#4
0!
0(
0'
0&
0%
0$
0#
1"
#5
1$
#6
0$
1#
#7
1$
