Samples/Verilog/sample7.v
module adder(output reg S, Cout, input A, B, Cin);
reg H, I, J;

always @(A or B or Cin) begin
    if ((A ^ B) == 1'b1) 
        H = 1'b1;
    else
        H = 1'b0;
    if ((A & B) == 1'b1)
        I = 1'b1;
    else
        I = 1'b0;
    if ((H & Cin) == 1'b1) 
        J = 1'b1;
    else
        J = 1'b0;
    if ((H ^ Cin) == 1'b1)
        S = 1'b1;
    else
        S = 1'b0;
    if ((I | J) == 1'b1)
        Cout = 1'b1;
    else
        Cout = 1'b0;
end
endmodule

Samples/Verilog/sample7_tb.v
module sample7_tb;
    reg A, B, Cin;
    wire S, Cout;
    adder uut(S, Cout, A, B, Cin);
    initial begin
        A = 0; B = 0; Cin = 0;
        #1 B = 1;
        #1 A = 1; B = 0;
        #1 B = 1;
        #1 A = 0; B = 0; Cin = 1;
        #1 B = 1;
        #1 A = 1; B = 0; 
        #1 B = 1;
    end
    initial begin
        $monitor("Time=%0t | A=%b B=%b Cin=%b | S=%b Cout=%b", $time, A, B, Cin, S, Cout);
        $dumpfile("sample7_tb.vcd");
        $dumpvars(0, sample7_tb);
    end
endmodule

Samples/Verilog/sample7_tb.vcd
$date
	Sun Mar 09 12:16:58 2025
$end
$version
	Icarus Verilog
$end
$timescale
	1s
$end
$scope module sample7_tb $end
$var wire 1 ! S $end
$var wire 1 " Cout $end
$var reg 1 # A $end
$var reg 1 $ B $end
$var reg 1 % Cin $end
$scope module uut $end
$var wire 1 # A $end
$var wire 1 $ B $end
$var wire 1 % Cin $end
$var reg 1 " Cout $end
$var reg 1 & H $end
$var reg 1 ' I $end
$var reg 1 ( J $end
$var reg 1 ! S $end
$upscope $end
$upscope $end
$enddefinitions $end
$comment Show the parameter values. $end
$dumpall
$end
#0
$dumpvars
0(
0'
0&
0%
0$
0#
0"
0!
$end
#1
1!
1&
1$
#2
0$
1#
#3
1"
0!
1'
0&
1$
#4
0"
1!
0'
1%
0$
0#
#5
1"
0!
1(
1&
1$
#6
0$
1#
#7
1!
0(
1'
0&
1$
