Samples/Verilog/sample4.v
module sample3 (output reg F, input A, B, C, D);
always @(*) begin
    if ((A ~| B) == 1'b1 && (~C) == 1'b1 && (C | D) == 1'b1) begin
        F = 1'b1;
    end
    else begin
        F = 1'b0;
    end
end
endmodule

Samples/Verilog/Samples1/sample4_tb.v
module sample3_tb;
    reg A, B, C, D;  
    wire F;       
    sample3 uut(F, A, B, C, D);
    initial begin
        A = 0; B = 0; C = 0; D = 0;
        #1 A = 0; B = 0; C = 0; D = 1;
        #1 C = 1; D = 0;
        #1 D = 1;
        #1 B = 1; C = 0; D = 0;
        #1 D = 1;
        #1 C = 1; D = 0;
        #1 D = 1;
        #1 A = 1; B = 0; C = 0; D = 0;
        #1 D = 1;
        #1 C = 1; D = 0;
        #1 D = 1;
        #1 B = 1; C = 0; D = 0;
        #1 D = 1;
        #1 C = 1; D = 0;
        #1 D = 1;
    end
    initial begin
        $monitor("Time=%0t | A=%b B=%b C=%b D=%b | F=%b", $time, A, B, C, D, F);
        $dumpfile("sample3_tb.vcd");
        $dumpvars(0, sample3_tb);
    end

endmodule

Samples/Verilog/sample3_tb.vcd
$date
	Sun Mar 09 08:26:37 2025
$end
$version
	Icarus Verilog
$end
$timescale
	1s
$end
$scope module sample3_tb $end
$var wire 1 ! F $end
$var reg 1 " A $end
$var reg 1 # B $end
$var reg 1 $ C $end
$var reg 1 % D $end
$scope module uut $end
$var wire 1 " A $end
$var wire 1 # B $end
$var wire 1 $ C $end
$var wire 1 % D $end
$var reg 1 ! F $end
$upscope $end
$upscope $end
$enddefinitions $end
$comment Show the parameter values. $end
$dumpall
$end
#0
$dumpvars
0%
0$
0#
0"
0!
$end
#1
1!
1%
#2
0!
0%
1$
#3
1%
#4
0%
0$
1#
#5
1%
#6
0%
1$
#7
1%
#8
0%
0$
0#
1"
#9
1%
#10
0%
1$
#11
1%
#12
0%
0$
1#
#13
1%
#14
0%
1$
#15
1%
