Samples/Verilog/Samples1/sample2.v
module sample2(A, B, C, F);
input A, B, C;
output F;
assign F = A & B | C;
endmodule

Samples/Verilog/sample2_tb.v
module sample2_tb;
    reg A, B, C;
    wire F;
    sample2 dut(A, B, C, F);
    initial begin
        $dumpfile("sample2.vcd");
        $dumpvars(0, sample2_tb);
        $display("A B C F");
        $monitor(A, " ", B, " ", C, " ", F);
        A = 0; B = 0; C = 0;
        #10 C = 1;
        #10 B = 1; C = 0;
        #10 C = 1;
        #10 A = 1; B = 0; C = 0;
        #10 C = 1;
        #10 B = 1; C = 0;
        #10 C = 1;
    end
endmodule

Samples/Verilog/Samples1/sample2.vcd
$date
	Sun Mar 09 07:17:19 2025
$end
$version
	Icarus Verilog
$end
$timescale
	1s
$end
$scope module sample2_tb $end
$var wire 1 ! F $end
$var reg 1 " A $end
$var reg 1 # B $end
$var reg 1 $ C $end
$scope module dut $end
$var wire 1 " A $end
$var wire 1 # B $end
$var wire 1 $ C $end
$var wire 1 ! F $end
$upscope $end
$upscope $end
$enddefinitions $end
$comment Show the parameter values. $end
$dumpall
$end
#0
$dumpvars
0$
0#
0"
0!
$end
#10
1!
1$
#20
0!
0$
1#
#30
1!
1$
#40
0!
0$
0#
1"
#50
1!
1$
#60
0$
1#
#70
1$
