Samples/Verilog/Samples1/sample8.v
module sample8(output reg F, input wire A, B, C);

always @(*) begin
    if ((A == 1'b0) && (B == 1'b0) && (C == 1'b0))
        F = 1'b1;
    else if ((A == 1'b0) && (B == 1'b1) && (C == 1'b0))
        F = 1'b1;
    else if ((A == 1'b1) && (B == 1'b1) && (C == 1'b0))
        F = 1'b1;
    else
        F = 1'b0;
end

endmodule

Samples/Verilog/Samples1/sample8_tb.v
module sample8_tb;
  reg A, B, C;
  wire F;
  
  sample8 uut (
    .F(F),
    .A(A),
    .B(B),
    .C(C)
  );
  
  initial begin
    {A, B, C} = 3'b000; #10;
    {A, B, C} = 3'b001; #10;
    {A, B, C} = 3'b010; #10;
    {A, B, C} = 3'b011; #10;
    {A, B, C} = 3'b100; #10;
    {A, B, C} = 3'b101; #10;
    {A, B, C} = 3'b110; #10;
    {A, B, C} = 3'b111; #10;
  end
  
  initial begin
    $monitor("Time=%0t | A=%b B=%b C=%b | F=%b", $time, A, B, C, F);
    $dumpfile("sample8_tb.vcd");
    $dumpvars(0, sample8_tb);
  end
endmodule

Samples/Verilog/Samples1/sample8_tb.vcd
$date
	Mon Apr 21 04:41:09 2025
$end
$version
	Icarus Verilog
$end
$timescale
	1s
$end
$scope module sample8_tb $end
$var wire 1 ! F $end
$var reg 1 " A $end
$var reg 1 # B $end
$var reg 1 $ C $end
$scope module uut $end
$var wire 1 " A $end
$var wire 1 # B $end
$var wire 1 $ C $end
$var reg 1 ! F $end
$upscope $end
$upscope $end
$enddefinitions $end
$comment Show the parameter values. $end
$dumpall
$end
#0
$dumpvars
0$
0#
0"
1!
$end
#10
0!
1$
#20
1!
1#
0$
#30
0!
1$
#40
1"
0#
0$
#50
1$
#60
1!
1#
0$
#70
0!
1$
