Samples/Verilog/Samples1/sample6.v
module sample_logic (output reg F, input A, B, C);
reg H, I, J;

always @(A or B or C) begin
    if ((~A & ~C) == 1'b1)
        H = 1'b1;
    else
        H = 1'b0;
    if ((A & ~H & ~B) == 1'b1)
        I = 1'b1;
    else
        I = 1'b0;
    if ((A & B & C) == 1'b1)
        J = 1'b1;
    else
        J = 1'b0;
    if ((I | J) == 1'b1)
        F = 1'b1;
    else
        F = 1'b0;
end
endmodule

Samples/Verilog/sample6_tb.v
module sample6_tb;
    reg A, B, C;
    wire F;
    sample_logic uut(F, A, B, C);
    initial begin
        A = 0; B = 0; C = 0;
        #1 A = 0; B = 0; C = 1;
        #1 A = 0; B = 1; C = 0;
        #1 A = 0; B = 1; C = 1;
        #1 A = 1; B = 0; C = 0;
        #1 A = 1; B = 0; C = 1;
        #1 A = 1; B = 1; C = 0;
        #1 A = 1; B = 1; C = 1;
    end
    initial begin
        $monitor("Time=%0t | A=%b B=%b C=%b | F=%b", $time, A, B, C, F);
        $dumpfile("sample6_tb.vcd");
        $dumpvars(0, sample6_tb);
    end
endmodule

Samples/Verilog/Samples1/sample6_tb.vcd
$date
	Sun Mar 09 20:19:06 2025
$end
$version
	Icarus Verilog
$end
$timescale
	1s
$end
$scope module sample6_tb $end
$var wire 1 ! F $end
$var reg 1 " A $end
$var reg 1 # B $end
$var reg 1 $ C $end
$scope module uut $end
$var wire 1 " A $end
$var wire 1 # B $end
$var wire 1 $ C $end
$var reg 1 ! F $end
$var reg 1 % H $end
$var reg 1 & I $end
$var reg 1 ' J $end
$upscope $end
$upscope $end
$enddefinitions $end
$comment Show the parameter values. $end
$dumpall
$end
#0
$dumpvars
0'
0&
0%
0$
0#
0"
0!
$end
#1
1%
1$
#2
0%
0$
1#
#3
1%
1$
#4
0$
0#
1"
#5
1$
#6
0$
1#
#7
1!
1'
1$
