Samples/Verilog/Output/tapa_problem2.v
module problem2(X, AB, AC, A, B, C);
    input A, B, C;
    output X, AB, AC;
    assign AB = A & B;
    assign AC = A & C;
    assign X = AB | AC;
endmodule

Samples/Verilog/Output/tapa_problem2_tb.v
module problem2_tb;
    reg A, B, C;
    wire X, AB, AC;
    problem2 dut(X, AB, AC, A, B, C);
    initial begin
        $dumpfile("simulation.vcd");
        $dumpvars(0, problem2_tb);
        $display("A B C AB AC X");
        $monitor(A, " ", B, " ", C, " ", AB, " ", AC, " ", X);
        A = 0; B = 0; C = 0;
        #10 C = 1;
        #10 B = 1; C = 0;
        #10 C = 1;
        #10 A = 1; B = 0; C = 0;
        #10 C = 1;
        #10 B = 1; C = 0;
        #10 C = 1;
    end
endmodule

Samples/Verilog/Output/simulation.vcd
$date
	Mon Feb 17 21:47:23 2025
$end
$version
	Icarus Verilog
$end
$timescale
	1s
$end
$scope module problem2_tb $end
$var wire 1 ! X $end
$var wire 1 " AC $end
$var wire 1 # AB $end
$var reg 1 $ A $end
$var reg 1 % B $end
$var reg 1 & C $end
$scope module dut $end
$var wire 1 $ A $end
$var wire 1 # AB $end
$var wire 1 " AC $end
$var wire 1 % B $end
$var wire 1 & C $end
$var wire 1 ! X $end
$upscope $end
$upscope $end
$enddefinitions $end
$comment Show the parameter values. $end
$dumpall
$end
#0
$dumpvars
0&
0%
0$
0#
0"
0!
$end
#10
1&
#20
0&
1%
#30
1&
#40
0&
0%
1$
#50
1!
1"
1&
#60
0"
1#
0&
1%
#70
1"
1&
